README.md
setup.py
test/test_path.py
varwwwhtml/__main__.py
varwwwhtml/server.py
varwwwhtml.egg-info/PKG-INFO
varwwwhtml.egg-info/SOURCES.txt
varwwwhtml.egg-info/dependency_links.txt
varwwwhtml.egg-info/top_level.txt