Metadata-Version: 2.1
Name: varwwwhtml
Version: 0.0.5
Summary: static web server cli tool
Home-page: https://github.com/mujdecisy/varwwwhtml
Author: mujdecisy
Author-email: mujdecisy@gmail.com
Keywords: python,static,web,server
Classifier: Programming Language :: Python :: 3
